pyspark_environment.py
local_pyspark_environment-0.1.1.dist-info/LICENSE
local_pyspark_environment-0.1.1.dist-info/METADATA
local_pyspark_environment-0.1.1.dist-info/WHEEL
local_pyspark_environment-0.1.1.dist-info/RECORD
